pemja-0.6.1.dist-info/RECORD
pemja-0.6.1.dist-info/WHEEL
pemja-0.6.1.dist-info/top_level.txt
pemja-0.6.1.dist-info/METADATA
pemja-0.6.1.dist-info/licenses/LICENSE
pemja/version.py
pemja/pemja_utils.cpython-313-darwin.so
pemja/redirect_stream.py
pemja/pemja_core.cpython-313-darwin.so
pemja/__init__.py
pemja/logger.py
